rejustify
