Metadata-Version: 2.1
Name: rejustify
Version: 1.0.3
Summary: Support for Rejustify API
Home-page: https://github.com/rejustify/python-module
Author: M. Wolski
Author-email: marcin@rejustify.com
License: UNKNOWN
Download-URL: https://github.com/rejustify/python-module/archive/1.0.3.tar.gz
Keywords: rejustify, ETL, data, economics, time-series
Platform: UNKNOWN
Classifier: Programming Language :: Python :: 3
Classifier: Development Status :: 4 - Beta
Classifier: License :: OSI Approved :: GNU General Public License v3 (GPLv3)
Classifier: Operating System :: OS Independent
Requires-Python: >=3.6
